[
  {
    "manufacturer": "Samsung",
    "market_name": "Galaxy Watch6",
    "codename": "fresh6ul",
    "model": "SM-R9450"
  },
  {
    "manufacturer": "Samsung",
    "market_name": "Galaxy Watch6",
    "codename": "fresh6ul",
    "model": "SM-R945F"
  },
  {
    "manufacturer": "Samsung",
    "market_name": "Galaxy Watch6",
    "codename": "fresh6ul",
    "model": "SM-R945N"
  },
  {
    "manufacturer": "Samsung",
    "market_name": "Galaxy Watch6",
    "codename": "fresh6ul",
    "model": "SM-R945U"
  }
]