[
  {
    "manufacturer": "Samsung",
    "market_name": "Galaxy S22+",
    "codename": "g0q",
    "model": "SM-S9060"
  },
  {
    "manufacturer": "Samsung",
    "market_name": "Galaxy S22+",
    "codename": "g0q",
    "model": "SM-S906E"
  },
  {
    "manufacturer": "Samsung",
    "market_name": "Galaxy S22+",
    "codename": "g0q",
    "model": "SM-S906N"
  },
  {
    "manufacturer": "Samsung",
    "market_name": "Galaxy S22+",
    "codename": "g0q",
    "model": "SM-S906U"
  },
  {
    "manufacturer": "Samsung",
    "market_name": "Galaxy S22+",
    "codename": "g0q",
    "model": "SM-S906U1"
  },
  {
    "manufacturer": "Samsung",
    "market_name": "Galaxy S22+",
    "codename": "g0q",
    "model": "SM-S906W"
  }
]