[
  {
    "manufacturer": "Huawei",
    "market_name": "Honor 7A",
    "codename": "HWDUA-M",
    "model": "DUA-L22"
  },
  {
    "manufacturer": "Huawei",
    "market_name": "Honor 7S",
    "codename": "HWDUA-M",
    "model": "DUA-AL00"
  },
  {
    "manufacturer": "Huawei",
    "market_name": "Honor 7S",
    "codename": "HWDUA-M",
    "model": "DUA-L22"
  },
  {
    "manufacturer": "Huawei",
    "market_name": "Honor 7S",
    "codename": "HWDUA-M",
    "model": "DUA-LX3"
  },
  {
    "manufacturer": "Huawei",
    "market_name": "荣耀畅玩7",
    "codename": "HWDUA-M",
    "model": "DUA-AL00"
  },
  {
    "manufacturer": "Huawei",
    "market_name": "荣耀畅玩7",
    "codename": "HWDUA-M",
    "model": "DUA-TL00"
  }
]