[
  {
    "manufacturer": "realme",
    "market_name": "realme  9i",
    "codename": "RED8C1L1",
    "model": "RMX3491"
  },
  {
    "manufacturer": "realme",
    "market_name": "realme 9i",
    "codename": "RED8C1L1",
    "model": "RMX3491"
  },
  {
    "manufacturer": "realme",
    "market_name": "realme 9i",
    "codename": "RED8C1L1",
    "model": "RMX3492"
  },
  {
    "manufacturer": "realme",
    "market_name": "realme 9i",
    "codename": "RED8C1L1",
    "model": "RMX3493"
  },
  {
    "manufacturer": "realme",
    "market_name": "realme 9i\t",
    "codename": "RED8C1L1",
    "model": "RMX3493"
  }
]