[
  {
    "manufacturer": "EVOFORCE1",
    "market_name": "FRC1-MOBI",
    "codename": "SEI800MOBI",
    "model": "FRC1-MOBI"
  },
  {
    "manufacturer": "EVOFORCE1",
    "market_name": "USA",
    "codename": "SEI800MOBI",
    "model": "FRC1-MOBI"
  },
  {
    "manufacturer": "EVOFORCE1",
    "market_name": "USA",
    "codename": "SEI800MOBI",
    "model": "MOBI-Buckeye"
  },
  {
    "manufacturer": "EVOFORCE1",
    "market_name": "USA\u0026Canada",
    "codename": "SEI800MOBI",
    "model": "FRC1-MOBI"
  },
  {
    "manufacturer": "EVOFORCE1",
    "market_name": "USA\u0026Canada",
    "codename": "SEI800MOBI",
    "model": "MOBI-SECTV"
  }
]