[
  {
    "manufacturer": "ASHIMA",
    "market_name": "OEM50ANDROID22/OEM55ANDROID22",
    "codename": "songshan",
    "model": "SmartTV 4K"
  },
  {
    "manufacturer": "Hisense",
    "market_name": "50A7H",
    "codename": "songshan",
    "model": "Smart TV"
  },
  {
    "manufacturer": "Hisense",
    "market_name": "A36",
    "codename": "songshan",
    "model": "2K Smart TV"
  },
  {
    "manufacturer": "Hisense",
    "market_name": "A55",
    "codename": "songshan",
    "model": "Smart TV"
  },
  {
    "manufacturer": "Hisense",
    "market_name": "A65",
    "codename": "songshan",
    "model": "SmartTV 4K FFM"
  },
  {
    "manufacturer": "Hisense",
    "market_name": "A6H/E6H/A6600H/A6500H/E7H/A6HA",
    "codename": "songshan",
    "model": "SmartTV 4K FFM"
  },
  {
    "manufacturer": "Hisense",
    "market_name": "U60H",
    "codename": "songshan",
    "model": "SmartTV 4K FFM"
  },
  {
    "manufacturer": "Hisense",
    "market_name": "U6H",
    "codename": "songshan",
    "model": "SmartTV 4K FFM"
  },
  {
    "manufacturer": "Hisense",
    "market_name": "U6H/A6H/U6G1",
    "codename": "songshan",
    "model": "SmartTV 4K"
  },
  {
    "manufacturer": "Hisense",
    "market_name": "songshan",
    "codename": "songshan",
    "model": "SmartTV 4K"
  },
  {
    "manufacturer": "Noblex",
    "market_name": "X7500",
    "codename": "songshan",
    "model": "SmartTV 4K"
  },
  {
    "manufacturer": "Noblex",
    "market_name": "X9500",
    "codename": "songshan",
    "model": "SmartTV 4K FFM"
  },
  {
    "manufacturer": "Panavox",
    "market_name": "50 google tv/58 google tv/65 google tv/75 google tv",
    "codename": "songshan",
    "model": "SmartTV 4K"
  },
  {
    "manufacturer": "Polytron",
    "market_name": "PLD43UG5959/PLD43BUG5959/PLD50UG5959/PLD50BUG5959/PLD55UG5959/",
    "codename": "songshan",
    "model": "POLYTRON4K"
  },
  {
    "manufacturer": "Riviera",
    "market_name": "HIKA5",
    "codename": "songshan",
    "model": "SmartTV 4K"
  },
  {
    "manufacturer": "Toshiba",
    "market_name": "C350LK",
    "codename": "songshan",
    "model": "Toshiba TV"
  },
  {
    "manufacturer": "Toshiba",
    "market_name": "C350LP/C350LI/E350LP/E450LP/C350LT/M550LT",
    "codename": "songshan",
    "model": "Toshiba TV"
  },
  {
    "manufacturer": "Toshiba",
    "market_name": "M550LK",
    "codename": "songshan",
    "model": "Toshiba TV with MIC"
  },
  {
    "manufacturer": "Toshiba",
    "market_name": "M550LP/M550LI",
    "codename": "songshan",
    "model": "Toshiba TV with MIC"
  },
  {
    "manufacturer": "Toshiba",
    "market_name": "V35LK",
    "codename": "songshan",
    "model": "2K Toshiba TV"
  },
  {
    "manufacturer": "Vu Televisions",
    "market_name": "43GloLED",
    "codename": "songshan",
    "model": "VU SMART TV"
  },
  {
    "manufacturer": "Vu Televisions",
    "market_name": "50CLED/55CLED/65CLED",
    "codename": "songshan",
    "model": "VU TV FFM"
  }
]