[
  {
    "manufacturer": "Daewoo",
    "market_name": "X7",
    "codename": "X7",
    "model": "X7"
  },
  {
    "manufacturer": "Dragontouch",
    "market_name": "X7",
    "codename": "X7",
    "model": "X7"
  },
  {
    "manufacturer": "Eks Mobility",
    "market_name": "x7",
    "codename": "X7",
    "model": "X7"
  },
  {
    "manufacturer": "Evercoss",
    "market_name": "X7",
    "codename": "X7",
    "model": "X7"
  },
  {
    "manufacturer": "Kenxinda",
    "market_name": "X7",
    "codename": "X7",
    "model": "X7"
  },
  {
    "manufacturer": "SBET",
    "market_name": "X7",
    "codename": "X7",
    "model": "X7"
  },
  {
    "manufacturer": "Selfix",
    "market_name": "X7",
    "codename": "X7",
    "model": "X7"
  },
  {
    "manufacturer": "Stylo",
    "market_name": "X7",
    "codename": "X7",
    "model": "X7"
  },
  {
    "manufacturer": "Techpad",
    "market_name": "X7",
    "codename": "X7",
    "model": "X7"
  },
  {
    "manufacturer": "USA111",
    "market_name": "Irulu X7",
    "codename": "X7",
    "model": "X7"
  },
  {
    "manufacturer": "Xmobile",
    "market_name": "X7",
    "codename": "X7",
    "model": "XMOBILE X7"
  }
]