{
  "manufacturer": "Acepad",
  "devices": [
    {
      "manufacturer": "",
      "market_name": "A121",
      "codename": "A121",
      "model": "A121"
    },
    {
      "manufacturer": "",
      "market_name": "A130",
      "codename": "A130",
      "model": "A130"
    },
    {
      "manufacturer": "",
      "market_name": "A130-2023",
      "codename": "A130-2023",
      "model": "A130-2023"
    },
    {
      "manufacturer": "",
      "market_name": "A131",
      "codename": "A131",
      "model": "A131"
    },
    {
      "manufacturer": "",
      "market_name": "A131_14",
      "codename": "A131_14",
      "model": "A131_14"
    },
    {
      "manufacturer": "",
      "market_name": "A140",
      "codename": "A140",
      "model": "A140"
    },
    {
      "manufacturer": "",
      "market_name": "A145",
      "codename": "A145",
      "model": "A145"
    },
    {
      "manufacturer": "",
      "market_name": "A150",
      "codename": "A150",
      "model": "A150"
    },
    {
      "manufacturer": "",
      "market_name": "A150_14",
      "codename": "A150_14",
      "model": "A150_14"
    },
    {
      "manufacturer": "",
      "market_name": "A170",
      "codename": "A170",
      "model": "A170"
    },
    {
      "manufacturer": "",
      "market_name": "A171_14",
      "codename": "A171_14",
      "model": "A171_14"
    },
    {
      "manufacturer": "",
      "market_name": "AX1",
      "codename": "AX1",
      "model": "AX1"
    }
  ]
}