{
  "manufacturer": "JREN",
  "devices": [
    {
      "manufacturer": "",
      "market_name": "J10",
      "codename": "J10",
      "model": "J10"
    },
    {
      "manufacturer": "",
      "market_name": "J10PLUS",
      "codename": "J10PLUS",
      "model": "J10PLUS"
    },
    {
      "manufacturer": "",
      "market_name": "J10PRO",
      "codename": "J10PRO",
      "model": "J10PRO"
    },
    {
      "manufacturer": "",
      "market_name": "J11PLUS",
      "codename": "J11PLUS",
      "model": "J11PLUS"
    },
    {
      "manufacturer": "",
      "market_name": "J7",
      "codename": "J7",
      "model": "J7"
    },
    {
      "manufacturer": "",
      "market_name": "JR-101",
      "codename": "JR-101",
      "model": "JR-101"
    },
    {
      "manufacturer": "",
      "market_name": "JR-802",
      "codename": "JR-802",
      "model": "JR-802"
    },
    {
      "manufacturer": "",
      "market_name": "JR-J71",
      "codename": "JR-J71",
      "model": "JR-J71"
    },
    {
      "manufacturer": "",
      "market_name": "JR-J8",
      "codename": "JR-J8",
      "model": "JR-J8"
    },
    {
      "manufacturer": "",
      "market_name": "JR_J1063",
      "codename": "JR_J1063",
      "model": "JR_J1063"
    },
    {
      "manufacturer": "",
      "market_name": "JR_J7",
      "codename": "JR_J7",
      "model": "JR_J7"
    }
  ]
}