{
  "manufacturer": "Korea Telecom",
  "devices": [
    {
      "manufacturer": "",
      "market_name": "KG3100",
      "codename": "KG3100",
      "model": "KG3100"
    },
    {
      "manufacturer": "",
      "market_name": "KG4100",
      "codename": "KG4100",
      "model": "KG4100"
    },
    {
      "manufacturer": "",
      "market_name": "KI1101",
      "codename": "KI1101",
      "model": "KI1101"
    },
    {
      "manufacturer": "",
      "market_name": "KSTB6188",
      "codename": "KSTB6188",
      "model": "KSTB6188"
    },
    {
      "manufacturer": "",
      "market_name": "MA4000",
      "codename": "MA4000",
      "model": "MA4000"
    },
    {
      "manufacturer": "",
      "market_name": "MA4100",
      "codename": "MA4100",
      "model": "MA4100"
    },
    {
      "manufacturer": "",
      "market_name": "MAR4510C",
      "codename": "MAR4510C",
      "model": "MAR4510C"
    }
  ]
}