{
  "manufacturer": "Unihertz",
  "devices": [
    {
      "manufacturer": "",
      "market_name": "Atom",
      "codename": "Atom",
      "model": "Atom"
    },
    {
      "manufacturer": "",
      "market_name": "Atom_L",
      "codename": "Atom_L",
      "model": "Atom_L"
    },
    {
      "manufacturer": "",
      "market_name": "Atom_XL",
      "codename": "Atom_XL",
      "model": "Atom_XL"
    },
    {
      "manufacturer": "",
      "market_name": "Jelly 2E",
      "codename": "Jelly_2E",
      "model": "Jelly 2E"
    },
    {
      "manufacturer": "",
      "market_name": "Jelly Star",
      "codename": "Jelly_Star",
      "model": "Jelly Star"
    },
    {
      "manufacturer": "",
      "market_name": "Jelly2",
      "codename": "Jelly2",
      "model": "Jelly2"
    },
    {
      "manufacturer": "",
      "market_name": "Jelly2_JP",
      "codename": "Jelly2_JP",
      "model": "Jelly2_JP"
    },
    {
      "manufacturer": "",
      "market_name": "Luna",
      "codename": "Luna",
      "model": "Luna"
    },
    {
      "manufacturer": "",
      "market_name": "TANK 01",
      "codename": "TANK_01",
      "model": "TANK 01"
    },
    {
      "manufacturer": "",
      "market_name": "TickTock-E",
      "codename": "UNIA62",
      "model": "UNIA62_S01"
    },
    {
      "manufacturer": "",
      "market_name": "TickTock-S",
      "codename": "TickTock-S",
      "model": "TickTock-S"
    },
    {
      "manufacturer": "",
      "market_name": "Ticktock",
      "codename": "Ticktock",
      "model": "Ticktock"
    },
    {
      "manufacturer": "",
      "market_name": "Titan",
      "codename": "Titan",
      "model": "Titan"
    },
    {
      "manufacturer": "",
      "market_name": "Titan Slim",
      "codename": "Titan_Slim",
      "model": "Titan Slim"
    },
    {
      "manufacturer": "",
      "market_name": "Titan pocket",
      "codename": "Titan_pocket",
      "model": "Titan pocket"
    }
  ]
}